converter/__init__.py
converter/converter.py
energy_converter-0.4.dist-info/METADATA
energy_converter-0.4.dist-info/WHEEL
energy_converter-0.4.dist-info/top_level.txt
energy_converter-0.4.dist-info/RECORD
