Metadata-Version: 2.4
Name: energy-converter
Version: 0.4
Summary: Converter for translating from different time intervals and different units of measure
Home-page: https://github.com/Artem.Pleshakov/energy-converter
Author: Artem Pleshakov
Author-email: Artem.Pleshakov@imby.energy
Classifier: Programming Language :: Python :: 3
Classifier: License :: OSI Approved :: MIT License
Classifier: Operating System :: OS Independent
Requires-Python: >=3.6
Requires-Dist: pandas
Dynamic: author
Dynamic: author-email
Dynamic: classifier
Dynamic: home-page
Dynamic: requires-dist
Dynamic: requires-python
Dynamic: summary
